{
  "jalali": {
    "from": "از",
    "to": "تا",
    "status": {
      "year": "سال",
      "month": "ماه",
      "date": "روز"
    },
    "months": [
      "فروردین",
      "اردیبهشت",
      "خرداد",
      "تیر",
      "مرداد",
      "شهریور",
      "مهر",
      "آبان",
      "آذر",
      "دی",
      "بهمن",
      "اسفند"
    ],
    "days": [
      "شنبه",
      "یکشنبه",
      "دوشنبه",
      "سه‌شنبه",
      "چهارشنبه",
      "پنج‌شنبه",
      "جمعه"
    ]
  },
  "gregorian": {
    "from": "From",
    "to": "To",
    "status": {
      "year": "year",
      "month": "month",
      "date": "date"
    },
    "months": [
      "January",
      "February",
      "March",
      "April",
      "May",
      "June",
      "July",
      "August",
      "September",
      "October",
      "November",
      "December"
    ],
    "days": [
      "Sunday",
      "Monday",
      "Tuesday",
      "Wednesday",
      "Thursday",
      "Friday",
      "Saturday"
    ]
  }
}
